peek/__init__.py
peek/peek.py
peek_python-26.0.1.dist-info/METADATA
peek_python-26.0.1.dist-info/WHEEL
peek_python-26.0.1.dist-info/top_level.txt
peek_python-26.0.1.dist-info/RECORD
