Metadata-Version: 2.4
Name: peek-python
Version: 26.0.1
Summary: peek - like print, but easy
Author-email: Ruud van der Ham <rt.van.der.ham@gmail.com>
Project-URL: Homepage, https://github.com/salabim/peek
Project-URL: Repository, https://github.com/salabim/peek
Classifier: Development Status :: 5 - Production/Stable
Classifier: Programming Language :: Python :: 3 :: Only
Requires-Python: >=3.9
Requires-Dist: asttokens>=3.0.0
Requires-Dist: colorama>=0.4.6
Requires-Dist: executing>=2.2.0
Requires-Dist: six>=1.17.0
Requires-Dist: tomli>=2.2.1
